embed-model/__init__.py
embed-model/modulo.py
embed_model/__init__.py
embed_model/buttons.py
embed_model/menus.py
embed_model/modals.py
embed_model/modulo.py
embed_model-0.4.4.dist-info/METADATA
embed_model-0.4.4.dist-info/WHEEL
embed_model-0.4.4.dist-info/top_level.txt
embed_model-0.4.4.dist-info/RECORD
