Metadata-Version: 2.2
Name: embed_model
Version: 0.4.4
Summary: Um modelo de embeds não oficial para discord.py. Feito em Português.
Home-page: https://github.com/LucaCunha001/DiscordEmbedModel
Author: Luca Cunha (Frisk)
Classifier: Programming Language :: Python :: 3
Classifier: License :: OSI Approved :: MIT License
Classifier: Operating System :: OS Independent
Classifier: Topic :: Software Development :: Libraries :: Python Modules
Requires-Python: >=3.8
Requires-Dist: discord
Dynamic: author
Dynamic: classifier
Dynamic: description
Dynamic: description-content-type
Dynamic: home-page
Dynamic: requires-dist
Dynamic: requires-python
Dynamic: summary
